simjb/__init__.py
simjb/token.py
simjb/token_test.py
simjb/src/dict.txt
simjb/src/simple-jieba_flow_v1_20191016-0347.png
simjb-0.2.0.dist-info/LICENSE
simjb-0.2.0.dist-info/METADATA
simjb-0.2.0.dist-info/WHEEL
simjb-0.2.0.dist-info/top_level.txt
simjb-0.2.0.dist-info/zip-safe
simjb-0.2.0.dist-info/RECORD
