Metadata-Version: 2.1
Name: simjb
Version: 0.2.0
Summary: A simple version of jieba.
Home-page: https://github.com/Ailln/simple-jieba
Author: Ailln
Author-email: kinggreenhall@gmail.com
License: MIT License
Platform: UNKNOWN
Classifier: Programming Language :: Python :: 3
Classifier: License :: OSI Approved :: MIT License
Classifier: Operating System :: OS Independent
Requires-Python: >=3.6
License-File: LICENSE
Requires-Dist: setuptools (>=40.6.3)
